Metadata-Version: 2.1
Name: django4-rest-swagger
Version: 1.0.1
Summary: Swagger UI for Django 4 & Django REST Framework 3+
Home-page: https://github.com/JorgeSalgado7/django4-rest-swagger
Author: Jorge Salgado
Author-email: contacto@jorgesalgado.com.mx
License: FreeBSD License
Platform: UNKNOWN
License-File: LICENSE
